pycop/__init__.py
pycop/simulation.py
pycop/utils.py
pycop/bivariate/__init__.py
pycop/bivariate/archimedean.py
pycop/bivariate/copula.py
pycop/bivariate/empirical.py
pycop/bivariate/estimation.py
pycop/bivariate/gaussian.py
pycop/bivariate/mixture.py
pycop/bivariate/student.py
pycop-0.0.13.dist-info/LICENSE
pycop-0.0.13.dist-info/METADATA
pycop-0.0.13.dist-info/WHEEL
pycop-0.0.13.dist-info/top_level.txt
pycop-0.0.13.dist-info/RECORD
