Metadata-Version: 2.1
Name: pycop
Version: 0.0.13
Summary: Copula for multivariate dependence modeling
Home-page: https://github.com/maximenc/pycop/
Download-URL: https://github.com/maximenc/pycop/
Author: Maxime N
Author-email: maxime.nlc@proton.me
License-File: LICENSE
